ALUHierarchical8bit.v
// Code your design here

//8-Bit ALU

module alu8(a,b,opcode,out);
  input [7:0] a,b;
  input [3:0] opcode;
  output reg [7:0] out;
  wire c_out,b_out;
  wire [2:0] op_main;
  wire op;
  assign op_main = opcode[3:1];
  assign op = opcode[0];

  wire [7:0] adder_out,subtractor_out,logic_out,shift_out;
  
  
  adder u1(.a(a),.b(b),.c_in(op),.sum(adder_out),.c_out(c_out));
  subtractor u2(.a(a), .b(b), .b_in(op), .difference(subtractor_out),.b_out(b_out));
  logicoperations u3(.a(a),.b(b),.sel({2'b00, op}),.out(logic_out));
  shiftoperations u4(.a(a),.opt({1'b0, op}),.result(shift_out));
  
  always @(*) begin
    case (op_main)
      2'b00: out = adder_out;
      2'b01: out = subtractor_out;
      2'b10: out = logic_out;
      2'b11: out = shift_out;
      default: out = 8'b0;
    endcase
    
  end
endmodule



//8-Bit Adder
module adder(a,b,c_in,sum,c_out);
  input [7:0] a,b;
  input c_in;
  output [7:0] sum;
  output c_out;
  assign {c_out,sum} = a + b + c_in;
  
endmodule

//8-bit subtractor

module subtractor (a,b,b_in,difference,b_out);
  input [7:0] a,b;
  input b_in;
  output [7:0] difference;
  output b_out;
  assign {b_out,difference} = {1'b0,a} - b - b_in;
endmodule

//Logic Operators

module logicoperations (a,b,sel,out);
  input [7:0] a,b;
  input [2:0] sel;
  output reg [7:0] out;
  
always @(*) begin
    case (sel)
      3'b000: out = a & b;
      3'b001: out = a | b;
      3'b010: out = ~a;
      3'b011: out = ~b;
      3'b100: out = a ^ b;
      3'b101: out = a ~^ b;
      default: out = 8'b0;
    endcase
  end
endmodule
//Shift Register

module shiftoperations (a,opt,result);
  input [7:0] a;
  input [1:0] opt;
  output reg [7:0] result;
  always @(*) begin
    case (opt)
      2'b00: result = a<<1;
      2'b01: result = a>>1;
      default:result = 8'b0;
    endcase
  end
endmodule

alu-hierarchical8bit/testbench.sv
// Code your testbench here
// or browse Examples
module alu8_tb;

  // Inputs
  reg [7:0] a, b;
  reg [2:0] opcode;
  wire [7:0] out;
  
  // Instantiate ALU
  alu8 alu8(.a(a), .b(b), .opcode(opcode), .out(out));

  integer i;
  integer fd;

  initial begin
    $dumpfile("dump.vcd");
    $dumpvars(1, alu8_tb);
    
    
    // Open a file to write output
    fd = $fopen("alu_output.txt", "w");
    if (fd == 0) begin
      $display("Error opening file!");
      $finish;
    end

    // Write column headers
    $fwrite(fd, "Time, A, B, Opcode, Out\n");

    //$monitor("Time=%0t | a=%b, b=%b | opcode=%b | out=%b", 
             // $time, a, b, opcode, out);

	// Edge case 1: A = 0, B = 0
    a = 8'b00000000;
    b = 8'b00000000;
    for (i = 0; i < 8; i = i + 1) begin
      #5 opcode = i;
    end

    // Edge case 2: A = 255, B = 255
    a = 8'b11111111;
    b = 8'b11111111;
    for (i = 0; i < 8; i = i + 1) begin
      #5 opcode = i;
      #1 $fwrite(fd, "%0t, %0d, %0d, %0d, %0d\n", $time, a, b, opcode, out);
    end

    // Edge case 3: A = alternating, B = alternating
    a = 8'b10101010;
    b = 8'b01010101;
    for (i = 0; i < 8; i = i + 1) begin
      #5 opcode = i;
      #1 $fwrite(fd, "%0t, %0d, %0d, %0d, %0d\n", $time, a, b, opcode, out);
    end

    // Random test cases
    for (i = 0; i < 8; i = i + 1) begin
      #5;
      a = $random & 8'hFF;
      b = $random & 8'hFF;
      opcode = i;
      #1 $fwrite(fd, "%0t, %0d, %0d, %0d, %0d\n", $time, a, b, opcode, out);
    end
    
    $fclose(fd); // Close the file

    #10 $finish;
  end

endmodule

dump.vcd
$date
	Sat Jun 28 14:51:43 2025
$end
$version
	Icarus Verilog
$end
$timescale
	1s
$end
$scope module alu8_tb $end
$var wire 8 ! out [7:0] $end
$var reg 8 " a [7:0] $end
$var reg 8 # b [7:0] $end
$var reg 3 $ opcode [2:0] $end
$var integer 32 % fd [31:0] $end
$var integer 32 & i [31:0] $end
$upscope $end
$enddefinitions $end
$comment Show the parameter values. $end
$dumpall
$end
#0
$dumpvars
b0 &
b10000000000000000000000000000011 %
bx $
b0 #
b0 "
b0 !
$end
#5
b1 &
b0 $
#10
b1 !
b10 &
b1 $
#15
b0 !
b11 &
b10 $
#20
b11111111 !
b100 &
b11 $
#25
b0 !
b101 &
b100 $
#30
b110 &
b101 $
#35
b111 &
b110 $
#40
b1111111 !
b11111111 #
b11111111 "
b0 &
b111 $
#45
b11111110 !
b0 $
#46
b1 &
#51
b11111111 !
b1 $
#52
b10 &
#57
b0 !
b10 $
#58
b11 &
#63
b11111111 !
b11 $
#64
b100 &
#69
b100 $
#70
b101 &
#75
b101 $
#76
b110 &
#81
b11111110 !
b110 $
#82
b111 &
#87
b1111111 !
b111 $
#88
b1010101 !
b1010101 #
b10101010 "
b0 &
#93
b11111111 !
b0 $
#94
b1 &
#99
b0 !
b1 $
#100
b10 &
#105
b1010101 !
b10 $
#106
b11 &
#111
b1010100 !
b11 $
#112
b100 &
#117
b0 !
b100 $
#118
b101 &
#123
b11111111 !
b101 $
#124
b110 &
#129
b1010100 !
b110 $
#130
b111 &
#135
b1010101 !
b111 $
#136
b0 &
#141
b10100101 !
b0 $
b10000001 #
b100100 "
#142
b1 &
#147
b1101101 !
b1 $
b1100011 #
b1001 "
#148
b10 &
#153
b10000000 !
b10 $
b10001101 #
b1101 "
#154
b11 &
#159
b1010010 !
b11 $
b10010 #
b1100101 "
#160
b100 &
#165
b1 !
b100 $
b1101 #
b1 "
#166
b101 &
#171
b1111111 !
b101 $
b111101 #
b1110110 "
#172
b110 &
#177
b11011010 !
b110 $
b10001100 #
b11101101 "
#178
b111 &
#183
b1111100 !
b111 $
b11000110 #
b11111001 "
#184
b1000 &
